pwatch
